plugin/__init__.py
plugin/artifactory_repository.py
mlflow_jfrog_plugin-1.0.1.dist-info/LICENSE
mlflow_jfrog_plugin-1.0.1.dist-info/METADATA
mlflow_jfrog_plugin-1.0.1.dist-info/WHEEL
mlflow_jfrog_plugin-1.0.1.dist-info/entry_points.txt
mlflow_jfrog_plugin-1.0.1.dist-info/top_level.txt
mlflow_jfrog_plugin-1.0.1.dist-info/RECORD
