Metadata-Version: 2.1
Name: mlflow-jfrog-plugin
Version: 1.0.1
Summary: Plugin to store MLFlow experiments artifacts on JFrog Artifactory
Home-page: https://github.com/jfrog/mlflow-jfrog-plugin
Author: JFrog
Author-email: pypi@jfrog.com
License: Apache License 2.0
Requires-Python: >=3.9
License-File: LICENSE
Requires-Dist: mlflow
Requires-Dist: requests >=2.31.0
